odoo10_addon_stock_removal_location_by_priority-10.0.1.0.0.99.dev5-py2.7-nspkg.pth
odoo/addons/stock_removal_location_by_priority/README.rst
odoo/addons/stock_removal_location_by_priority/__init__.py
odoo/addons/stock_removal_location_by_priority/__manifest__.py
odoo/addons/stock_removal_location_by_priority/init_hook.py
odoo/addons/stock_removal_location_by_priority/i18n/de.po
odoo/addons/stock_removal_location_by_priority/i18n/es.po
odoo/addons/stock_removal_location_by_priority/i18n/fi.po
odoo/addons/stock_removal_location_by_priority/i18n/fr.po
odoo/addons/stock_removal_location_by_priority/i18n/it.po
odoo/addons/stock_removal_location_by_priority/i18n/pt_BR.po
odoo/addons/stock_removal_location_by_priority/i18n/ro.po
odoo/addons/stock_removal_location_by_priority/i18n/sl.po
odoo/addons/stock_removal_location_by_priority/i18n/stock_removal_location_by_priority.pot
odoo/addons/stock_removal_location_by_priority/i18n/zh_CN.po
odoo/addons/stock_removal_location_by_priority/models/__init__.py
odoo/addons/stock_removal_location_by_priority/models/stock_config_settings.py
odoo/addons/stock_removal_location_by_priority/models/stock_location.py
odoo/addons/stock_removal_location_by_priority/models/stock_quant.py
odoo/addons/stock_removal_location_by_priority/security/stock_security.xml
odoo/addons/stock_removal_location_by_priority/static/description/icon.png
odoo/addons/stock_removal_location_by_priority/tests/__init__.py
odoo/addons/stock_removal_location_by_priority/tests/test_stock_removal_location_by_priority.py
odoo/addons/stock_removal_location_by_priority/views/res_config_settings_views.xml
odoo/addons/stock_removal_location_by_priority/views/stock_location_view.xml
odoo10_addon_stock_removal_location_by_priority-10.0.1.0.0.99.dev5.dist-info/METADATA
odoo10_addon_stock_removal_location_by_priority-10.0.1.0.0.99.dev5.dist-info/RECORD
odoo10_addon_stock_removal_location_by_priority-10.0.1.0.0.99.dev5.dist-info/WHEEL
odoo10_addon_stock_removal_location_by_priority-10.0.1.0.0.99.dev5.dist-info/namespace_packages.txt
odoo10_addon_stock_removal_location_by_priority-10.0.1.0.0.99.dev5.dist-info/top_level.txt
